flask_cloudflared.py
flask_cloudflared-0.0.14.dist-info/LICENSE
flask_cloudflared-0.0.14.dist-info/METADATA
flask_cloudflared-0.0.14.dist-info/WHEEL
flask_cloudflared-0.0.14.dist-info/top_level.txt
flask_cloudflared-0.0.14.dist-info/RECORD
