Metadata-Version: 2.1
Name: flask-cloudflared
Version: 0.0.14
Summary: Start a TryCloudflare Tunnel from your flask app.
Home-page: https://github.com/UWUplus/flask-cloudflared
Author: Ralf Rademacher
Keywords: flask cloudflared
Classifier: Programming Language :: Python :: 3.6
Classifier: License :: OSI Approved :: Apache Software License
Classifier: Operating System :: OS Independent
License-File: LICENSE
